README.md
setup.py
sdi_pandas/__init__.py
sdi_pandas.egg-info/PKG-INFO
sdi_pandas.egg-info/SOURCES.txt
sdi_pandas.egg-info/dependency_links.txt
sdi_pandas.egg-info/requires.txt
sdi_pandas.egg-info/top_level.txt
sdi_pandas/anonymizeData/__init__.py
sdi_pandas/anonymizeData/anonymizeData.py
sdi_pandas/castColumns/__init__.py
sdi_pandas/castColumns/castColumns.py
sdi_pandas/dropColumns/__init__.py
sdi_pandas/dropColumns/dropColumns.py
sdi_pandas/fromCSV/__init__.py
sdi_pandas/fromCSV/fromCSV.py
sdi_pandas/fuzzyjoin/__init__.py
sdi_pandas/fuzzyjoin/fuzzyjoin.py
sdi_pandas/groupby/__init__.py
sdi_pandas/groupby/groupby.py
sdi_pandas/join/__init__.py
sdi_pandas/join/join.py
sdi_pandas/linRegressionPredict/__init__.py
sdi_pandas/linRegressionPredict/linRegressionPredict.py
sdi_pandas/linRegressionTrain/__init__.py
sdi_pandas/linRegressionTrain/linRegressionTrain.py
sdi_pandas/oneHotEncoding/__init__.py
sdi_pandas/oneHotEncoding/oneHotEncoding.py
sdi_pandas/sample/__init__.py
sdi_pandas/sample/sample.py
sdi_pandas/selectValues/__init__.py
sdi_pandas/selectValues/selectValues.py
sdi_pandas/setValue/__init__.py
sdi_pandas/setValue/setValue.py
sdi_pandas/splitSample/__init__.py
sdi_pandas/splitSample/splitSample.py
sdi_pandas/toCSV/__init__.py
sdi_pandas/toCSV/toCSV.py
sdi_pandas/transposeColumn/__init__.py
sdi_pandas/transposeColumn/transposeColumn.py