Metadata-Version: 2.1
Name: sdi-pandas
Version: 0.0.27
Summary: List of operators using the pandas module for processing the input
Home-page: https://github.com/thhapke/sdi_pandas/
Author: Thorsten Hapke
Author-email: thorsten.hapke@sap.com
License: UNKNOWN
Keywords: SAP Data Intelligence,pandas,operator
Platform: UNKNOWN
Classifier: Programming Language :: Python :: 3.5
Classifier: Programming Language :: Python :: 3.6
Classifier: Programming Language :: Python :: 3.7
Classifier: License :: OSI Approved :: MIT License
Classifier: Operating System :: OS Independent
